.bumpversion.cfg
.gitignore
CHANGELOG.md
MANIFEST.in
README.rst
justfile
requirements-dev.txt
requirements-flake8.txt
requirements.txt
setup.py
template-version.txt
tox.ini
src/fhs_pia_wireguard_netns/__init__.py
src/fhs_pia_wireguard_netns/__version__.py
src/fhs_pia_wireguard_netns/cli.py
src/fhs_pia_wireguard_netns/config.py
src/fhs_pia_wireguard_netns/fhs_pia_wireguard_netns.py
src/fhs_pia_wireguard_netns/wg_netns.py
src/fhs_pia_wireguard_netns.egg-info/PKG-INFO
src/fhs_pia_wireguard_netns.egg-info/SOURCES.txt
src/fhs_pia_wireguard_netns.egg-info/dependency_links.txt
src/fhs_pia_wireguard_netns.egg-info/entry_points.txt
src/fhs_pia_wireguard_netns.egg-info/requires.txt
src/fhs_pia_wireguard_netns.egg-info/top_level.txt
src/fhs_pia_wireguard_netns/pia_class/__init__.py
src/fhs_pia_wireguard_netns/pia_class/config.py
src/fhs_pia_wireguard_netns/pia_class/server.py
src/fhs_pia_wireguard_netns/pia_class/token.py
src/fhs_pia_wireguard_netns/pia_class/data/ca.rsa.4096.crt
src/fhs_pia_wireguard_netns/wg_class/__init__.py
src/fhs_pia_wireguard_netns/wg_class/keys.py
tests/test_sample.py