Metadata-Version: 2.1
Name: fhs-pia-wireguard-netns
Version: 0.1.5
Summary: configure network namespace wireguard for pia
Home-page: https://github.com/foxhunt72/fhs-pia-wireguard-netns
Author: Richard de Vos
Author-email: rdevos72@gmail.com
License: MIT license
Classifier: Development Status :: 4 - Beta
Classifier: Programming Language :: Python
Classifier: Programming Language :: Python :: 3
Classifier: Programming Language :: Python :: 3.6
Classifier: Programming Language :: Python :: 3.7
Classifier: Programming Language :: Python :: 3.8
Classifier: Programming Language :: Python :: 3.9
Classifier: Programming Language :: Python :: 3.10
Requires-Dist: typer[all]
Requires-Dist: requests
Requires-Dist: wgconfig
Requires-Dist: fhs_wireguard_namespace
Requires-Dist: pyyaml
Requires-Dist: setuptools
